sqliteai_vector-0.9.70.data/purelib/sqlite_vector/__init__.py
sqliteai_vector-0.9.70.data/purelib/sqlite_vector/_version.py
sqliteai_vector-0.9.70.data/purelib/sqlite_vector/binaries/vector.dll
sqliteai_vector-0.9.70.dist-info/licenses/LICENSE.md
sqliteai_vector-0.9.70.dist-info/METADATA
sqliteai_vector-0.9.70.dist-info/WHEEL
sqliteai_vector-0.9.70.dist-info/top_level.txt
sqliteai_vector-0.9.70.dist-info/RECORD
